pyboot/dataflowx/context/webmvc/__init__.py
pyboot_webmvc-1.3.3.dist-info/licenses/LICENSE
pyboot_webmvc-1.3.3.dist-info/METADATA
pyboot_webmvc-1.3.3.dist-info/WHEEL
pyboot_webmvc-1.3.3.dist-info/top_level.txt
pyboot_webmvc-1.3.3.dist-info/RECORD
